calculator_math_operations/__init__.py
calculator_math_operations/add.py
calculator_math_operations/subtract.py
calculator_math_operations-0.0.1.dist-info/METADATA
calculator_math_operations-0.0.1.dist-info/WHEEL
calculator_math_operations-0.0.1.dist-info/top_level.txt
calculator_math_operations-0.0.1.dist-info/RECORD
