Metadata-Version: 2.4
Name: calculator-math-operations
Version: 0.0.1
Summary: Pacote para operações matemáticas básicas
Home-page: https://github.com/LuthLucas/math-operations-package.git
Author: LuthLucas
Author-email: lucasmenezesfontes@gmail.com
Requires-Python: >=3.5
Dynamic: author
Dynamic: author-email
Dynamic: description
Dynamic: description-content-type
Dynamic: home-page
Dynamic: requires-python
Dynamic: summary
